setup.py
torch_sparse_solve.cpp
torch_sparse_solve.py
torch_sparse_solve.egg-info/PKG-INFO
torch_sparse_solve.egg-info/SOURCES.txt
torch_sparse_solve.egg-info/dependency_links.txt
torch_sparse_solve.egg-info/top_level.txt