Metadata-Version: 2.1
Name: torch-sparse-solve
Version: 0.0.4
Summary:  A sparse KLU solver for PyTorch 
Home-page: https://github.com/flaport/torch_sparse_solve
Author: Floris Laporte
Author-email: floris.laporte@gmail.com
License: UNKNOWN
Platform: UNKNOWN
Classifier: Development Status :: 3 - Alpha
Classifier: Programming Language :: Python :: 3
Classifier: Programming Language :: Python :: 2.7
Classifier: License :: OSI Approved :: GNU Lesser General Public License v2 (LGPLv2)
Classifier: Operating System :: OS Independent
Classifier: Topic :: Scientific/Engineering :: Mathematics
